MANIFEST.in
README.rst
setup.py
twistit/__init__.py
twistit/_errorhandling.py
twistit/_events.py
twistit/_mock.py
twistit/_testing.py
twistit/_timeout.py
twistit/_yieldefer.py
twistit/test_errorhandling.py
twistit/test_events.py
twistit/test_mock.py
twistit/test_testing.py
twistit/test_timeout.py
twistit/test_yielddefer.py
twistit.egg-info/PKG-INFO
twistit.egg-info/SOURCES.txt
twistit.egg-info/dependency_links.txt
twistit.egg-info/requires.txt
twistit.egg-info/top_level.txt