Metadata-Version: 1.0
Name: twistit
Version: 0.2.2
Summary: Handy tools for the twisted framework
Home-page: https://github.com/smurn/twistit
Author: Stefan C. Mueller
Author-email: scm@smurn.org
License: UNKNOWN
Platform: UNKNOWN
